special_functions/besseli.pxd
special_functions/cbessely.pxd
special_functions/besselh.pxd
special_functions/besselj.pxd
special_functions/besselk.pxd
special_functions/_complex_functions.pxd
special_functions/cbesselk.cpython-39-darwin.so
special_functions/cbesseli.pxd
special_functions/cbesselh.pxd
special_functions/bessely.pxd
special_functions/besselj.cpython-39-darwin.so
special_functions/cbesselj.pxd
special_functions/cbesselk.pxd
special_functions/__init__.pxd
special_functions/__init__.py
special_functions/cbesselj.cpython-39-darwin.so
special_functions/__config__.py
special_functions/besselk.cpython-39-darwin.so
special_functions/lngamma.cpython-39-darwin.so
special_functions/besselh.cpython-39-darwin.so
special_functions/cbesseli.cpython-39-darwin.so
special_functions/cython_wrappers.py
special_functions/lngamma.pxd
special_functions/bessely.cpython-39-darwin.so
special_functions/_complex_functions.cpython-39-darwin.so
special_functions/besseli.cpython-39-darwin.so
special_functions/cbesselh.cpython-39-darwin.so
special_functions/cbessely.cpython-39-darwin.so
special_functions/.dylibs/libgfortran.5.dylib
special_functions/.dylibs/libquadmath.0.dylib
special_functions/.dylibs/libgcc_s.1.1.dylib
special_functions-0.3.7.dist-info/RECORD
special_functions-0.3.7.dist-info/WHEEL
special_functions-0.3.7.dist-info/LICENSE.txt
special_functions-0.3.7.dist-info/METADATA
