Metadata-Version: 2.1
Name: special_functions
Version: 0.3.7
Summary: Cython and Python API for special functions.
Keywords: special-functions bessel-function gamma-function
Home-page: https://ameli.github.io/special_functions/
Author-Email: Siavash Ameli <sameli@berkeley.edu>
License: Copyright (c) 2020-2022, Siavash Ameli <sameli@berkeley.edu>
Classifier: Programming Language :: Cython
Classifier: Programming Language :: Python :: 3.9
Classifier: Programming Language :: Python :: 3.10
Classifier: Programming Language :: Python :: 3.11
Classifier: Programming Language :: Python :: 3.12
Classifier: Programming Language :: Python :: Implementation :: CPython
Classifier: Programming Language :: Python :: Implementation :: PyPy
Classifier: License :: OSI Approved :: MIT License
Classifier: Operating System :: POSIX :: Linux
Classifier: Operating System :: Microsoft :: Windows
Classifier: Operating System :: MacOS
Classifier: Natural Language :: English
Classifier: Intended Audience :: Science/Research
Classifier: Intended Audience :: Developers
Classifier: Topic :: Software Development
Classifier: Topic :: Software Development :: Libraries :: Python Modules
Project-URL: Homepage, https://ameli.github.io/special_functions/
Project-URL: Documentation, https://ameli.github.io/special_functions/
Project-URL: Source, https://github.com/ameli/special_functions/
Project-URL: Download, https://github.com/ameli/special_functions/archive/main.zip
Project-URL: Tracker, https://github.com/ameli/special_functions/issues
Requires-Python: >=3.8
